[{"bookSourceName":"第一会所小说","bookSourceType":0,"bookSourceUrl":"https:\/\/162.252.9.25\/","customOrder":0,"enabled":true,"enabledCookieJar":true,"enabledExplore":true,"exploreUrl":"[\n  {\n    \"title\": \"文学作者区\",\n    \"url\": \"forum\/forumdisplay.php?fid=322&filter=0&orderby=dateline&ascdesc=DESC&page={{page}}\",\n    \"style\": {\n      \"layout_flexGrow\": 1,\n      \"layout_flexBasisPercent\":1\n    }\n  },\n  {\n    \"title\": \"原创人生区\",\n    \"url\": \"\",\n    \"style\": {\n      \"layout_flexGrow\": 1,\n      \"layout_flexBasisPercent\":1\n    }\n  },\n  {\n    \"title\": \"玄学幻想\",\n    \"url\": \"forum\/forumdisplay.php?fid=383&filter=type&typeid=1326&orderby=dateline&ascdesc=DESC&page={{page}}\",\n    \"style\": {\n      \"layout_flexGrow\": 1\n    }\n  },\n  {\n    \"title\": \"魔法奇幻\",\n    \"url\": \"forum\/forumdisplay.php?fid=383&filter=type&typeid=1327&orderby=dateline&ascdesc=DESC&page={{page}}\",\n    \"style\": {\n      \"layout_flexGrow\": 1\n    }\n  },\n  {\n    \"title\": \"修真仙侠\",\n    \"url\": \"forum\/forumdisplay.php?fid=383&filter=type&typeid=1328&orderby=dateline&ascdesc=DESC&page={{page}}\",\n    \"style\": {\n      \"layout_flexGrow\": 1\n    }\n  },\n  {\n    \"title\": \"侠骨柔情\",\n    \"url\": \"forum\/forumdisplay.php?fid=383&filter=type&typeid=1329&orderby=dateline&ascdesc=DESC&page={{page}}\",\n    \"style\": {\n      \"layout_flexGrow\": 1\n    }\n  },\n  {\n    \"title\": \"科幻未来\",\n    \"url\": \"forum\/forumdisplay.php?fid=383&filter=type&typeid=1330&orderby=dateline&ascdesc=DESC&page={{page}}\",\n    \"style\": {\n      \"layout_flexGrow\": 1\n    }\n  },\n  {\n    \"title\": \"同人衍生\",\n    \"url\": \"forum\/forumdisplay.php?fid=383&filter=type&typeid=1331&orderby=dateline&ascdesc=DESC&page={{page}}\",\n    \"style\": {\n      \"layout_flexGrow\": 1\n    }\n  },\n  {\n    \"title\": \"穿越架空\",\n    \"url\": \"forum\/forumdisplay.php?fid=383&filter=type&typeid=1332&orderby=dateline&ascdesc=DESC&page={{page}}\",\n    \"style\": {\n      \"layout_flexGrow\": 1\n    }\n  },\n  {\n    \"title\": \"催眠控制\",\n    \"url\": \"forum\/forumdisplay.php?fid=383&filter=type&typeid=1333&orderby=dateline&ascdesc=DESC&page={{page}}\",\n    \"style\": {\n      \"layout_flexGrow\": 1\n    }\n  },\n  {\n    \"title\": \"历史古香\",\n    \"url\": \"forum\/forumdisplay.php?fid=383&filter=type&typeid=1334&orderby=dateline&ascdesc=DESC&page={{page}}\",\n    \"style\": {\n      \"layout_flexGrow\": 1\n    }\n  },\n  {\n    \"title\": \"青葱校园\",\n    \"url\": \"forum\/forumdisplay.php?fid=383&filter=type&typeid=1336&orderby=dateline&ascdesc=DESC&page={{page}}\",\n    \"style\": {\n      \"layout_flexGrow\": 1\n    }\n  },\n  {\n    \"title\": \"乡土田园\",\n    \"url\": \"forum\/forumdisplay.php?fid=383&filter=type&typeid=1337&orderby=dateline&ascdesc=DESC&page={{page}}\",\n    \"style\": {\n      \"layout_flexGrow\": 1\n    }\n  },\n  {\n    \"title\": \"唯美纯爱\",\n    \"url\": \"forum\/forumdisplay.php?fid=383&filter=type&typeid=1338&orderby=dateline&ascdesc=DESC&page={{page}}\",\n    \"style\": {\n      \"layout_flexGrow\": 1\n    }\n  },\n  {\n    \"title\": \"凌辱虐情\",\n    \"url\": \"forum\/forumdisplay.php?fid=383&filter=type&typeid=1340&orderby=dateline&ascdesc=DESC&page={{page}}\",\n    \"style\": {\n      \"layout_flexGrow\": 1\n    }\n  },\n  {\n    \"title\": \"禁忌之恋\",\n    \"url\": \"forum\/forumdisplay.php?fid=383&filter=type&typeid=1341&orderby=dateline&ascdesc=DESC&page={{page}}\",\n    \"style\": {\n      \"layout_flexGrow\": 1\n    }\n  },\n  {\n    \"title\": \"星梦奇缘\",\n    \"url\": \"forum\/forumdisplay.php?fid=383&filter=type&typeid=1342&orderby=dateline&ascdesc=DESC&page={{page}}\",\n    \"style\": {\n      \"layout_flexGrow\": 1\n    }\n  },\n  {\n    \"title\": \"玉足恋物\",\n    \"url\": \"forum\/forumdisplay.php?fid=383&filter=type&typeid=1343&orderby=dateline&ascdesc=DESC&page={{page}}\",\n    \"style\": {\n      \"layout_flexGrow\": 1\n    }\n  },\n  {\n    \"title\": \"秀色冰恋\",\n    \"url\": \"forum\/forumdisplay.php?fid=383&filter=type&typeid=1344&orderby=dateline&ascdesc=DESC&page={{page}}\",\n    \"style\": {\n      \"layout_flexGrow\": 1\n    }\n  },\n  {\n    \"title\": \"强奸迷奸\",\n    \"url\": \"forum\/forumdisplay.php?fid=383&filter=type&typeid=1345&orderby=dateline&ascdesc=DESC&page={{page}}\",\n    \"style\": {\n      \"layout_flexGrow\": 1\n    }\n  },\n  {\n    \"title\": \"另类小众\",\n    \"url\": \"forum\/forumdisplay.php?fid=383&filter=type&typeid=1346&orderby=dateline&ascdesc=DESC&page={{page}}\",\n    \"style\": {\n      \"layout_flexGrow\": 1\n    }\n  },\n  {\n    \"title\": \"女警英雄\",\n    \"url\": \"forum\/forumdisplay.php?fid=383&filter=type&typeid=1371&orderby=dateline&ascdesc=DESC&page={{page}}\",\n    \"style\": {\n      \"layout_flexGrow\": 1\n    }\n  },\n]","lastUpdateTime":"1761464303887","respondTime":180000,"ruleBookInfo":[],"ruleContent":{"content":"class.t_msgfont@html","replaceRegex":"","sourceRegex":""},"ruleExplore":{"author":"class.author@tag.a@text","bookList":"tag.table.-3@tag.tbody&&tag.table.-2@tag.tbody","bookUrl":"class.folder@tag.a@href","intro":"class.author@tag.em@text","name":"tag.a.2@text"},"ruleSearch":{"author":"","bookList":"","bookUrl":"","checkKeyWord":"","coverUrl":"","intro":"","name":""},"ruleToc":{"chapterList":"<js>[1]<\/js>","chapterName":"<js>book.name<\/js>","chapterUrl":""},"searchUrl":"","weight":0}]